{
  "stages": [
    {
      "label": "boundary_micro_v3_targeted_1x",
      "corpus": "training/corpus/kernel_c17_boundary_micro_v3_targeted_1x.jsonl",
      "prefix": "c17_boundary_micro_v3_targeted_1x",
      "base": "core/c17_contrast_angle_1200_e4.pt",
      "max_epoch": 1,
      "lr": 0.00001,
      "order": 0
    },
    {
      "label": "boundary_micro_v3_balanced_1x",
      "corpus": "training/corpus/kernel_c17_boundary_micro_v3_balanced_1x.jsonl",
      "prefix": "c17_boundary_micro_v3_balanced_1x",
      "base": "core/c17_contrast_angle_1200_e4.pt",
      "max_epoch": 1,
      "lr": 0.00001,
      "order": 1
    },
    {
      "label": "boundary_micro_v3_targeted_2x",
      "corpus": "training/corpus/kernel_c17_boundary_micro_v3_targeted_2x.jsonl",
      "prefix": "c17_boundary_micro_v3_targeted_2x",
      "base": "core/c17_contrast_angle_1200_e4.pt",
      "max_epoch": 1,
      "lr": 0.00001,
      "order": 2
    },
    {
      "label": "boundary_micro_v3_balanced_2x",
      "corpus": "training/corpus/kernel_c17_boundary_micro_v3_balanced_2x.jsonl",
      "prefix": "c17_boundary_micro_v3_balanced_2x",
      "base": "core/c17_contrast_angle_1200_e4.pt",
      "max_epoch": 1,
      "lr": 0.00001,
      "order": 3
    }
  ],
  "eval_suites": [
    {
      "name": "boundary_v2",
      "tests": "training/corpus_admin/probe_sets/c17_boundary_v2.jsonl"
    }
  ],
  "probes": [
    "who are you?",
    "what is your name?",
    "what is a dog?",
    "what does a dog look like?",
    "what is a tree?",
    "is a tree a mammal?",
    "is a plant an animal?",
    "what is the name of this dog?",
    "what is an airport used for?",
    "what does an airplane do?",
    "how does an airplane work?",
    "what happened at my school today?"
  ],
  "decision_policy": {
    "current_best": "core/c17_contrast_angle_1200_e4.pt",
    "promote_if": {
      "default_avg_score_at_least": 0.905,
      "default_pass_rate_at_least": "5/7",
      "boundary_v2_avg_score_at_least": 0.85
    },
    "rollback_if": {
      "default_avg_score_below": 0.85,
      "default_pass_rate_below": "4/7"
    },
    "next_if_micro_helps": "Use the best micro branch as evidence for tutor-loop repair dose; do not stack more repair until it beats the protected default gate.",
    "next_if_micro_fails": "Keep protected best and move toward concept-card tutor sessions rather than broad hand-built repair files."
  }
}
