{
  "max_epoch": 4,
  "stages": [
    {
      "label": "sorted",
      "corpus": "training/corpus/kernel_c17_ladder_1200_e1.jsonl",
      "prefix": "c17_ladder_1200",
      "base": "core/kernel_e1_focus_repair.pt",
      "order": 0
    },
    {
      "label": "contrast",
      "corpus": "training/corpus/kernel_c17_contrast_angle_1200_e1.jsonl",
      "prefix": "c17_contrast_angle_1200",
      "base": "core/kernel_e1_focus_repair.pt",
      "order": 1
    }
  ],
  "probes": [
    "who are you?",
    "what is your name?",
    "what is a dog?",
    "what does a dog look like?",
    "is a dog a machine?",
    "what is an airport used for?",
    "what does an airplane do?",
    "how does an airplane work?",
    "what is water?",
    "what is a tree?",
    "what happened at my school today?",
    "what is the name of this dog?"
  ]
}
